{
	"name": "deadMenu",
	"layers": [
		{
			"name": "Layer 0",
			"overriden": 0,
			"instances": [
				{
					"type": "Sprite6",
					"properties": {
						"initially-visible": true,
						"initial-animation": "Default",
						"initial-frame": 0,
						"enable-collisions": false,
						"live-preview": false
					},
					"uid": 432,
					"instanceVariables": {},
					"behaviors": {},
					"world": {
						"x": 734,
						"y": 89.5,
						"width": 2623,
						"height": 1244,
						"originX": 0.5,
						"originY": 0.5,
						"color": [
							1,
							1,
							1,
							1
						],
						"angle": 0
					}
				},
				{
					"type": "Text10",
					"properties": {
						"text": "You lost :(",
						"enable-bbcode": false,
						"font": "Arial",
						"size": 36,
						"line-height": 0,
						"bold": false,
						"italic": false,
						"color": [
							0,
							0,
							0,
							1
						],
						"horizontal-alignment": "left",
						"vertical-alignment": "top",
						"wrapping": "word",
						"initially-visible": true,
						"origin": "top-left"
					},
					"uid": 83,
					"instanceVariables": {},
					"behaviors": {},
					"world": {
						"x": 378,
						"y": 133,
						"width": 245,
						"height": 69,
						"originX": 0,
						"originY": 0,
						"color": [
							1,
							1,
							1,
							1
						],
						"angle": 0
					}
				},
				{
					"type": "Button6",
					"properties": {
						"type": "button",
						"text": "Restart",
						"tooltip": "",
						"initially-visible": true,
						"enabled": true,
						"auto-font-size": true,
						"checked": false,
						"id": ""
					},
					"uid": 84,
					"instanceVariables": {},
					"behaviors": {},
					"world": {
						"x": 447,
						"y": 300,
						"width": 72,
						"height": 24,
						"originX": 0,
						"originY": 0,
						"color": [
							1,
							1,
							1,
							1
						]
					}
				},
				{
					"type": "timeTaken",
					"properties": {
						"text": "",
						"enable-bbcode": false,
						"font": "Arial",
						"size": 18,
						"line-height": 0,
						"bold": false,
						"italic": false,
						"color": [
							0,
							0,
							1,
							1
						],
						"horizontal-alignment": "center",
						"vertical-alignment": "top",
						"wrapping": "word",
						"initially-visible": true,
						"origin": "top-left"
					},
					"uid": 101,
					"instanceVariables": {},
					"behaviors": {},
					"world": {
						"x": 224,
						"y": 209,
						"width": 538,
						"height": 53,
						"originX": 0,
						"originY": 0,
						"color": [
							1,
							1,
							1,
							1
						],
						"angle": 0
					}
				}
			],
			"sid": 834269101780610,
			"effectTypes": [],
			"isInitiallyVisible": true,
			"color": [
				1,
				1,
				1,
				1
			],
			"backgroundColor": [
				1,
				1,
				1,
				1
			],
			"isTransparent": false,
			"parallaxX": 1,
			"parallaxY": 1,
			"scaleRate": 1,
			"forceOwnTexture": false,
			"useRenderCells": false,
			"blendMode": "normal",
			"global": false
		}
	],
	"sid": 314210663976903,
	"nonworld-instances": [],
	"effectTypes": [],
	"width": 1708,
	"height": 960,
	"unboundedScrolling": false,
	"eventSheet": "deadMenuSheet"
}