{
	"name": "LucyDead",
	"plugin-id": "Sprite",
	"sid": 691619103617248,
	"isGlobal": false,
	"instanceVariables": [],
	"behaviorTypes": [
		{
			"behaviorId": "solid",
			"name": "Solid",
			"sid": 531905886927886
		},
		{
			"behaviorId": "Platform",
			"name": "Platform",
			"sid": 728962202053241
		}
	],
	"effectTypes": [],
	"animations": {
		"items": [
			{
				"frames": [
					{
						"width": 64,
						"height": 64,
						"originX": 0.5,
						"originY": 0.5,
						"originalSource": "",
						"exportFormat": "png",
						"exportQuality": 0.8,
						"imageSpriteId": 7,
						"collisionPoly": {
							"points": [
								0.138671875,
								0.76953125,
								0.244140625,
								0.693359375,
								0.53515625,
								0.75,
								0.875,
								0.802734375,
								0.87109375,
								0.93359375,
								0.146484375,
								0.931640625
							]
						},
						"duration": 1
					}
				],
				"sid": 578902148923798,
				"name": "Animation 1",
				"isLooping": false,
				"isPingPong": false,
				"repeatCount": 1,
				"repeatTo": 0,
				"speed": 5
			}
		],
		"subfolders": []
	}
}